cleora-1.2.3.dist-info/METADATA
cleora-1.2.3.dist-info/WHEEL
cleora-1.2.3.dist-info/license_files/LICENSE
cleora.libs/libssl-f8da170d.so.1.1
cleora.libs/libcrypto-75174c47.so.1.1
cleora/__init__.py
cleora/cleora.cpython-39-x86_64-linux-gnu.so
cleora-1.2.3.dist-info/RECORD
