Metadata-Version: 2.1
Name: cleora
Version: 1.2.3
Classifier: Programming Language :: Rust
Classifier: Programming Language :: Python :: Implementation :: CPython
Classifier: Programming Language :: Python :: Implementation :: PyPy
License-File: LICENSE
Summary: Cleora is a general-purpose model for efficient, scalable learning of stable and inductive entity embeddings for heterogeneous relational data.
Requires-Python: >=3.7
